{
  "$schema": "https://developer.microsoft.com/json-schemas/fabric/item/report/definition/visualContainer/2.7.0/schema.json",
  "name": "471280c01b6e96d6dbfc",
  "position": {
    "x": 1087.0935960591132,
    "y": 87.783251231527089,
    "z": 15000,
    "height": 39.901477832512313,
    "width": 161.37931034482759,
    "tabOrder": 15000
  },
  "visual": {
    "visualType": "textbox",
    "objects": {
      "general": [
        {
          "properties": {
            "paragraphs": [
              {
                "textRuns": [
                  {
                    "value": "Irregularidades",
                    "textStyle": {
                      "fontFamily": "Arial",
                      "fontSize": "16pt"
                    }
                  }
                ]
              }
            ]
          }
        }
      ]
    },
    "visualContainerObjects": {
      "background": [
        {
          "properties": {
            "transparency": {
              "expr": {
                "Literal": {
                  "Value": "100D"
                }
              }
            }
          }
        }
      ]
    },
    "drillFilterOtherVisuals": true
  }
}